origamibot/__init__.py
origamibot/core/__init__.py
origamibot/core/api_request.py
origamibot/core/bot.py
origamibot/core/callbacks.py
origamibot/core/commands.py
origamibot/core/exceptions.py
origamibot/core/sthread.py
origamibot/core/teletypes/__init__.py
origamibot/core/teletypes/animation.py
origamibot/core/teletypes/audio.py
origamibot/core/teletypes/base/__init__.py
origamibot/core/teletypes/base/field.py
origamibot/core/teletypes/base/inline_query_result.py
origamibot/core/teletypes/base/input_media.py
origamibot/core/teletypes/base/input_message_content.py
origamibot/core/teletypes/base/telegram_structure.py
origamibot/core/teletypes/bot_command.py
origamibot/core/teletypes/callback_query.py
origamibot/core/teletypes/chat.py
origamibot/core/teletypes/chat_member.py
origamibot/core/teletypes/chat_permissions.py
origamibot/core/teletypes/chat_photo.py
origamibot/core/teletypes/chosen_inline_result.py
origamibot/core/teletypes/command_scope.py
origamibot/core/teletypes/contact.py
origamibot/core/teletypes/dice.py
origamibot/core/teletypes/document.py
origamibot/core/teletypes/encrypted_credentials.py
origamibot/core/teletypes/encrypted_passport_element.py
origamibot/core/teletypes/file.py
origamibot/core/teletypes/force_reply.py
origamibot/core/teletypes/game.py
origamibot/core/teletypes/inline_keyboard_button.py
origamibot/core/teletypes/inline_keyboard_markup.py
origamibot/core/teletypes/inline_query.py
origamibot/core/teletypes/inline_query_result/__init__.py
origamibot/core/teletypes/inline_query_result/article.py
origamibot/core/teletypes/inline_query_result/audio.py
origamibot/core/teletypes/inline_query_result/cached_audio.py
origamibot/core/teletypes/inline_query_result/cached_document.py
origamibot/core/teletypes/inline_query_result/cached_gif.py
origamibot/core/teletypes/inline_query_result/cached_mpeg4_gif.py
origamibot/core/teletypes/inline_query_result/cached_sticker.py
origamibot/core/teletypes/inline_query_result/cached_video.py
origamibot-2.3.4.dist-info/METADATA
origamibot-2.3.4.dist-info/LICENSE
origamibot-2.3.4.dist-info/WHEEL
origamibot-2.3.4.dist-info/RECORD
