Metadata-Version: 2.1
Name: origamibot
Version: 2.3.4
Summary: Library for creating bots for telegram with Python.
Home-page: https://github.com/cmd410/OrigamiBot
License: MIT
Author: Crystal Melting Dot
Author-email: stresspassing@gmail.com
Requires-Python: >=3.7,<4.0
Classifier: License :: OSI Approved :: MIT License
Classifier: Programming Language :: Python :: 3
Classifier: Programming Language :: Python :: 3.7
Classifier: Programming Language :: Python :: 3.8
Classifier: Programming Language :: Python :: 3.9
Classifier: Programming Language :: Python :: 3.10
Classifier: Programming Language :: Python :: 3.11
Provides-Extra: telegram-text
Requires-Dist: requests (>=2.25.1,<3.0.0)
Requires-Dist: telegram-text (>=0.1.0,<0.2.0) ; extra == "telegram-text"
Project-URL: Repository, https://github.com/cmd410/OrigamiBot
